{
  "regionId": "Cherkasy",
  "lastUpdated": "2026-01-02T22:05:00.869Z",
  "fact": {
    "data": {
      "1767391200": {
        "GPV1.1": {
          "1": "yes",
          "2": "yes",
          "3": "yes",
          "4": "yes",
          "5": "yes",
          "6": "yes",
          "7": "yes",
          "8": "yes",
          "9": "yes",
          "10": "yes",
          "11": "yes",
          "12": "yes",
          "13": "yes",
          "14": "yes",
          "15": "yes",
          "16": "yes",
          "17": "no",
          "18": "no",
          "19": "no",
          "20": "yes",
          "21": "yes",
          "22": "yes",
          "23": "yes",
          "24": "yes"
        },
        "GPV1.2": {
          "1": "yes",
          "2": "yes",
          "3": "yes",
          "4": "yes",
          "5": "yes",
          "6": "yes",
          "7": "yes",
          "8": "yes",
          "9": "yes",
          "10": "yes",
          "11": "yes",
          "12": "yes",
          "13": "yes",
          "14": "yes",
          "15": "yes",
          "16": "yes",
          "17": "no",
          "18": "no",
          "19": "yes",
          "20": "yes",
          "21": "yes",
          "22": "yes",
          "23": "yes",
          "24": "yes"
        },
        "GPV2.1": {
          "1": "yes",
          "2": "yes",
          "3": "yes",
          "4": "yes",
          "5": "yes",
          "6": "yes",
          "7": "yes",
          "8": "yes",
          "9": "yes",
          "10": "yes",
          "11": "yes",
          "12": "yes",
          "13": "yes",
          "14": "yes",
          "15": "yes",
          "16": "yes",
          "17": "no",
          "18": "no",
          "19": "yes",
          "20": "yes",
          "21": "yes",
          "22": "yes",
          "23": "yes",
          "24": "yes"
        },
        "GPV2.2": {
          "1": "yes",
          "2": "yes",
          "3": "yes",
          "4": "yes",
          "5": "yes",
          "6": "yes",
          "7": "yes",
          "8": "yes",
          "9": "yes",
          "10": "yes",
          "11": "yes",
          "12": "yes",
          "13": "yes",
          "14": "yes",
          "15": "no",
          "16": "no",
          "17": "yes",
          "18": "yes",
          "19": "yes",
          "20": "yes",
          "21": "yes",
          "22": "yes",
          "23": "no",
          "24": "no"
        },
        "GPV3.1": {
          "1": "yes",
          "2": "yes",
          "3": "yes",
          "4": "yes",
          "5": "yes",
          "6": "yes",
          "7": "yes",
          "8": "yes",
          "9": "yes",
          "10": "yes",
          "11": "yes",
          "12": "yes",
          "13": "yes",
          "14": "yes",
          "15": "no",
          "16": "no",
          "17": "yes",
          "18": "yes",
          "19": "yes",
          "20": "yes",
          "21": "yes",
          "22": "yes",
          "23": "yes",
          "24": "yes"
        },
        "GPV3.2": {
          "1": "yes",
          "2": "yes",
          "3": "yes",
          "4": "yes",
          "5": "yes",
          "6": "yes",
          "7": "yes",
          "8": "yes",
          "9": "yes",
          "10": "yes",
          "11": "yes",
          "12": "yes",
          "13": "yes",
          "14": "yes",
          "15": "no",
          "16": "no",
          "17": "yes",
          "18": "yes",
          "19": "yes",
          "20": "yes",
          "21": "no",
          "22": "no",
          "23": "yes",
          "24": "yes"
        },
        "GPV4.1": {
          "1": "yes",
          "2": "yes",
          "3": "yes",
          "4": "yes",
          "5": "yes",
          "6": "yes",
          "7": "yes",
          "8": "yes",
          "9": "yes",
          "10": "yes",
          "11": "yes",
          "12": "yes",
          "13": "no",
          "14": "no",
          "15": "yes",
          "16": "yes",
          "17": "yes",
          "18": "yes",
          "19": "yes",
          "20": "yes",
          "21": "no",
          "22": "no",
          "23": "yes",
          "24": "yes"
        },
        "GPV4.2": {
          "1": "yes",
          "2": "yes",
          "3": "yes",
          "4": "yes",
          "5": "yes",
          "6": "yes",
          "7": "yes",
          "8": "yes",
          "9": "yes",
          "10": "yes",
          "11": "yes",
          "12": "yes",
          "13": "no",
          "14": "no",
          "15": "yes",
          "16": "yes",
          "17": "yes",
          "18": "yes",
          "19": "yes",
          "20": "yes",
          "21": "yes",
          "22": "yes",
          "23": "yes",
          "24": "yes"
        },
        "GPV5.1": {
          "1": "yes",
          "2": "yes",
          "3": "yes",
          "4": "yes",
          "5": "yes",
          "6": "yes",
          "7": "yes",
          "8": "yes",
          "9": "yes",
          "10": "yes",
          "11": "no",
          "12": "no",
          "13": "yes",
          "14": "yes",
          "15": "yes",
          "16": "yes",
          "17": "yes",
          "18": "yes",
          "19": "yes",
          "20": "yes",
          "21": "yes",
          "22": "yes",
          "23": "yes",
          "24": "yes"
        },
        "GPV5.2": {
          "1": "yes",
          "2": "yes",
          "3": "yes",
          "4": "yes",
          "5": "yes",
          "6": "yes",
          "7": "yes",
          "8": "yes",
          "9": "yes",
          "10": "yes",
          "11": "no",
          "12": "no",
          "13": "yes",
          "14": "yes",
          "15": "yes",
          "16": "yes",
          "17": "yes",
          "18": "yes",
          "19": "yes",
          "20": "yes",
          "21": "yes",
          "22": "yes",
          "23": "yes",
          "24": "yes"
        },
        "GPV6.1": {
          "1": "yes",
          "2": "yes",
          "3": "yes",
          "4": "yes",
          "5": "yes",
          "6": "yes",
          "7": "yes",
          "8": "yes",
          "9": "no",
          "10": "no",
          "11": "yes",
          "12": "yes",
          "13": "yes",
          "14": "yes",
          "15": "yes",
          "16": "yes",
          "17": "yes",
          "18": "yes",
          "19": "no",
          "20": "no",
          "21": "yes",
          "22": "yes",
          "23": "yes",
          "24": "yes"
        },
        "GPV6.2": {
          "1": "yes",
          "2": "yes",
          "3": "yes",
          "4": "yes",
          "5": "yes",
          "6": "yes",
          "7": "yes",
          "8": "yes",
          "9": "no",
          "10": "no",
          "11": "yes",
          "12": "yes",
          "13": "yes",
          "14": "yes",
          "15": "yes",
          "16": "yes",
          "17": "yes",
          "18": "yes",
          "19": "no",
          "20": "no",
          "21": "yes",
          "22": "yes",
          "23": "yes",
          "24": "yes"
        }
      }
    },
    "update": "03.01.2026 00:05",
    "today": 1767391200
  }
}